winrtqrabber/__init__.py
winrtqrabber/controller.py
winrtqrabber/view.py
winrtqrabber/winrtcapture.py
winrtqrabber-0.0.3.dist-info/LICENSE
winrtqrabber-0.0.3.dist-info/WHEEL
winrtqrabber-0.0.3.dist-info/METADATA
winrtqrabber-0.0.3.dist-info/RECORD
