Metadata-Version: 2.1
Name: winrtqrabber
Version: 0.0.3
Summary: Qr code scanner
Home-page: https://github.com/sander76/winrtqrabber
License: UNKNOWN
Keywords: wxpyton,winrt,webcam,scanner,qrcode,qr-code
Author: Sander Teunissen
Author-email: no_mail@nomail.com
Requires-Python: >=3.7
Classifier: License :: OSI Approved :: MIT License
Classifier: Development Status :: 4 - Beta
Classifier: Operating System :: Microsoft :: Windows :: Windows 10
Classifier: Programming Language :: Python :: 3.7
Classifier: Programming Language :: Python :: 3.8
Classifier: Programming Language :: Python :: 3.9
Classifier: Programming Language :: Python :: 3.10
Requires-Dist: wxpython
Requires-Dist: winrt
Requires-Dist: pylint ; extra == "dev"
Requires-Dist: nox ; extra == "dev"
Requires-Dist: pytest-cov ; extra == "dev"
Requires-Dist: coverage[toml]>=5.0.3 ; extra == "dev"
Requires-Dist: pre-commit ; extra == "dev"
Requires-Dist: pytest ; extra == "test"
Requires-Dist: pytest-asyncio ; extra == "test"
Requires-Dist: pytest-mock ; extra == "test"
Provides-Extra: dev
Provides-Extra: test
